mycalc/__init__.py
mycalc/calculator.py
calculator_practice-0.0.1.dist-info/LICENSE
calculator_practice-0.0.1.dist-info/METADATA
calculator_practice-0.0.1.dist-info/WHEEL
calculator_practice-0.0.1.dist-info/top_level.txt
calculator_practice-0.0.1.dist-info/RECORD
