Metadata-Version: 2.1
Name: calculator-practice
Version: 0.0.1
Summary: nice calculator
Home-page: https://github.com/Leejunso0/my-oss
Download-URL: https://github.com/Leejunso0/my-oss
Author: junsoo
Classifier: Programming Language :: Python :: 3
License-File: LICENSE
